{
    "resources": [
        {
            "title": "Open Source Guides",
            "author": "GitHub",
            "link": "https://opensource.guide/",
            "type": "Guide",
            "topics": "GitHub, Open Source"
        },
        {
            "title": "About pull requests",
            "author": "GitHub",
            "link": "https://docs.github.com/es/pull-requests/collaborating-with-pull-requests/proposing-changes-to-your-work-with-pull-requests/about-pull-requests",
            "type": "Docs",
            "topics": "GitHub"
        }
    ]
}